FEAS/ErrHandler.py
FEAS/ErrHandling.py
FEAS/ErrHandling2.py
FEAS/FBCast.py
FEAS/FBCasting.py
FEAS/FCmpInfo.py
FEAS/FCompany.py
FEAS/FDBStructure.py
FEAS/FEAS.py
FEAS/FEmployees.py
FEAS/FExitProc.py
FEAS/FExitRep.py
FEAS/FFindEmp.py
FEAS/FFlrDetail2.py
FEAS/FFlrReport.py
FEAS/FListExits.py
FEAS/FMonitor.py
FEAS/FMonitor2.py
FEAS/FMsgType.py
FEAS/FSensorMon.py
FEAS/FSysAdmin.py
FEAS/FdbCreation.py
FEAS/FeasDBCls.py
FEAS/FeasFrmCls.py
FEAS/FeasInputCls.py
FEAS/FeasLblCls.py
FEAS/FeasMsgCls.py
FEAS/MsgFormat.py
FEAS/MsgHandling.py
FEAS/Token.py
FEAS/__init__.py
FEAS/dbscript.py
FEAS/feasfloor.py
FEAS/setup.py
FEAS-0.0.2.dist-info/LICENSE
FEAS-0.0.2.dist-info/METADATA
FEAS-0.0.2.dist-info/WHEEL
FEAS-0.0.2.dist-info/top_level.txt
FEAS-0.0.2.dist-info/RECORD
