Metadata-Version: 2.1
Name: FEAS
Version: 0.0.2
Summary: Fire Evacuation Automation System
Home-page: https://github.com/tahiriqbal70/FEAS
Author: Tahir Iqbal
Author-email: Tahir Iqbal <tahiriqbal70@gmail.com>
License: MIT License
Project-URL: Homepage, https://github.com/tahiriqbal70/FEAS
Project-URL: Issues, https://github.com/tahiriqbal70/FEAS/issues
Classifier: Programming Language :: Python :: 3
Classifier: License :: OSI Approved :: MIT License
Classifier: Operating System :: Microsoft :: Windows :: Windows 10
Requires-Python: >=3.10
License-File: LICENSE
